{
    "dataType": "playListDetail",
    "title": "前任？不存在的。",
    "id": 2292620420,
    "cover": "http://p4.music.126.net/LE72hpGyAsUjdoPgo-LTAg==/109951163394384910.jpg?param=200y200",
    "desc": "<b>介绍：</b>\n相忘于江湖？不存在的。<br>\n还能做朋友？哇哦~那你不是好棒棒。<br>\n三段进阶式疗法专业治前任，没在怕的。<br>\n<br>\n【第一乐章】 <br>\n1-12 华语流行篇 “祝你幸福，百年不合。”<br>\n主题：这位前任你戏真的多，好气哦可是还是...<br>\n",
    "songs": [
        {
            "id": 515803379,
            "name": "别",
            "duration": "03:35",
            "singer": "薛之谦"
        },
        {
            "id": 27955653,
            "name": "你还要我怎样",
            "duration": "05:10",
            "singer": "薛之谦"
        },
        {
            "id": 28481103,
            "name": "你给我听好",
            "duration": "04:48",
            "singer": "陈奕迅"
        },
        {
            "id": 108864,
            "name": "突然累了",
            "duration": "04:08",
            "singer": "林俊杰"
        },
        {
            "id": 28095072,
            "name": "分手后不要做朋友 - (电视剧《回到爱以前》片尾曲)",
            "duration": "04:22",
            "singer": "梁文音"
        },
        {
            "id": 393419,
            "name": "最好不相见 - (电影《非诚勿扰2》片尾曲)",
            "duration": "05:02",
            "singer": "李漠"
        },
        {
            "id": 299042,
            "name": "请勿客气",
            "duration": "04:34",
            "singer": "王菲/软硬天师"
        },
        {
            "id": 299069,
            "name": "忘掉你像忘掉我",
            "duration": "04:23",
            "singer": "王菲"
        },
        {
            "id": 432509882,
            "name": "好爱好散",
            "duration": "04:43",
            "singer": "陈势安"
        },
        {
            "id": 523251118,
            "name": "说散就散 - (电影《前任3：再见前任》主题曲)",
            "duration": "04:02",
            "singer": "袁娅维"
        },
        {
            "id": 511920347,
            "name": "祝你幸福",
            "duration": "04:37",
            "singer": "李荣浩"
        },
        {
            "id": 31514961,
            "name": "百年不合",
            "duration": "04:16",
            "singer": "周柏豪"
        },
        {
            "id": 32451229,
            "name": "不要问我过得好不好",
            "duration": "02:30",
            "singer": "好妹妹乐队"
        },
        {
            "id": 35618531,
            "name": "旧情人，我是时间的新欢",
            "duration": "04:43",
            "singer": "尧十三"
        },
        {
            "id": 29787865,
            "name": "对不起没有人会相依为命",
            "duration": "05:15",
            "singer": "尧十三"
        },
        {
            "id": 292262,
            "name": "时过境迁",
            "duration": "04:46",
            "singer": "邵夷贝"
        },
        {
            "id": 38679344,
            "name": " 往事只能回味  - (电影《唐人街探案》推广曲)",
            "duration": "03:01",
            "singer": "好妹妹"
        },
        {
            "id": 28267047,
            "name": "啊朋友 再见",
            "duration": "05:03",
            "singer": "蒋明/冬子/刘东明/好妹妹乐队/钟立风/小河"
        },
        {
            "id": 29771089,
            "name": "他妈的 - (电影《推拿》片尾曲)",
            "duration": "05:18",
            "singer": "尧十三"
        },
        {
            "id": 27731424,
            "name": "该装就装",
            "duration": "03:52",
            "singer": "郝云"
        },
        {
            "id": 292254,
            "name": "我不相信爱情",
            "duration": "05:39",
            "singer": "邵夷贝"
        },
        {
            "id": 28590174,
            "name": "谁他妈没织过毛衣",
            "duration": "02:18",
            "singer": "李志"
        },
        {
            "id": 419373705,
            "name": "只不过是",
            "duration": "03:24",
            "singer": "花粥"
        },
        {
            "id": 460542191,
            "name": "一腔诗意喂了狗",
            "duration": "02:11",
            "singer": "花粥"
        },
        {
            "id": 93855,
            "name": "不要想得太多",
            "duration": "03:29",
            "singer": "杭天"
        },
        {
            "id": 479029380,
            "name": "千万不要以为，你永远都对",
            "duration": "04:29",
            "singer": "杭天"
        },
        {
            "id": 368731,
            "name": "别惹我",
            "duration": "04:10",
            "singer": "扭曲机器"
        },
        {
            "id": 167573,
            "name": "我不爱你",
            "duration": "04:52",
            "singer": "谢天笑"
        },
        {
            "id": 25950601,
            "name": "我不废话你也别废话",
            "duration": "00:27",
            "singer": "脑浊乐队"
        },
        {
            "id": 29144625,
            "name": "我说的就是我要干的",
            "duration": "03:50",
            "singer": "CMCB"
        },
        {
            "id": 28018236,
            "name": "Dont Talk About Money - (不要谈钱)",
            "duration": "03:25",
            "singer": "丝绒公路"
        },
        {
            "id": 93816,
            "name": "还给我吧,我的时间我的钱",
            "duration": "03:29",
            "singer": "杭天"
        },
        {
            "id": 368817,
            "name": "压抑不住的愤怒",
            "duration": "05:46",
            "singer": "扭曲机器"
        },
        {
            "id": 384680,
            "name": "有时候真想往你脸上灌一拳",
            "duration": "01:01",
            "singer": "透明杂志"
        },
        {
            "id": 360933,
            "name": "Hey bicth",
            "duration": "03:03",
            "singer": "Joyside"
        },
        {
            "id": 368191,
            "name": "You Suck",
            "duration": "03:45",
            "singer": "先知玛莉"
        },
        {
            "id": 356076,
            "name": "Leave Me",
            "duration": "03:47",
            "singer": "挂在盒子上"
        },
        {
            "id": 351066,
            "name": "I Hate You",
            "duration": "02:16",
            "singer": "Casino Demon"
        }
    ]
}